{"company":"companies/9","employee":"employees/1","orderedAt":"1997-05-02T00:00:00+00:00","requireAt":"1997-05-30T00:00:00+00:00","shippedAt":"1997-05-23T00:00:00+00:00","shipTo":{"line1":"12, rue des Bouchers","city":"Marseille","postalCode":"13008","country":"France"},"shipVia":"shippers/2","freight":11.06,"lines":[{"product":"products/36","productName":"Inlagd Sill","pricePerUnit":19.0,"quantity":30,"discount":0.0},{"product":"products/40","productName":"Boston Crab Meat","pricePerUnit":18.4,"quantity":15,"discount":0.1}],"id":"orders/278"}