{"company":"companies/25","employee":"employees/8","orderedAt":"1997-06-06T00:00:00+00:00","requireAt":"1997-07-04T00:00:00+00:00","shippedAt":"1997-06-09T00:00:00+00:00","shipTo":{"line1":"Berliner Platz 43","city":"München","postalCode":"80805","country":"Germany"},"shipVia":"shippers/1","freight":36.65,"lines":[{"product":"products/30","productName":"Nord-Ost Matjeshering","pricePerUnit":25.89,"quantity":20,"discount":0.0},{"product":"products/62","productName":"Tarte au sucre","pricePerUnit":49.3,"quantity":15,"discount":0.25}],"id":"orders/313"}