{"company":"companies/20","employee":"employees/8","orderedAt":"1997-06-17T00:00:00+00:00","requireAt":"1997-07-29T00:00:00+00:00","shippedAt":"1997-07-04T00:00:00+00:00","shipTo":{"line1":"Kirchgasse 6","city":"Graz","postalCode":"8010","country":"Austria"},"shipVia":"shippers/3","freight":26.06,"lines":[{"product":"products/14","productName":"Tofu","pricePerUnit":23.25,"quantity":11,"discount":0.15},{"product":"products/42","productName":"Singaporean Hokkien Fried Mee","pricePerUnit":14.0,"quantity":28,"discount":0.15}],"id":"orders/324"}