{"company":"companies/2","employee":"employees/3","orderedAt":"1997-08-08T00:00:00+00:00","requireAt":"1997-09-05T00:00:00+00:00","shippedAt":"1997-08-14T00:00:00+00:00","shipTo":{"line1":"Avda. de la Constitución 2222","city":"México D.F.","postalCode":"05021","country":"Mexico"},"shipVia":"shippers/1","freight":43.9,"lines":[{"product":"products/14","productName":"Tofu","pricePerUnit":23.25,"quantity":3,"discount":0.0},{"product":"products/42","productName":"Singaporean Hokkien Fried Mee","pricePerUnit":14.0,"quantity":5,"discount":0.0},{"product":"products/60","productName":"Camembert Pierrot","pricePerUnit":34.0,"quantity":10,"discount":0.0}],"id":"orders/378"}