{"company":"companies/1","employee":"employees/6","orderedAt":"1997-08-25T00:00:00+00:00","requireAt":"1997-09-22T00:00:00+00:00","shippedAt":"1997-09-02T00:00:00+00:00","shipTo":{"line1":"Obere Str. 57","city":"Berlin","postalCode":"12209","country":"Germany"},"shipVia":"shippers/1","freight":29.46,"lines":[{"product":"products/28","productName":"Rössle Sauerkraut","pricePerUnit":45.6,"quantity":15,"discount":0.25},{"product":"products/39","productName":"Chartreuse verte","pricePerUnit":18.0,"quantity":21,"discount":0.25},{"product":"products/46","productName":"Spegesild","pricePerUnit":12.0,"quantity":2,"discount":0.25}],"id":"orders/396"}