{"company":"companies/56","employee":"employees/3","orderedAt":"1997-09-26T00:00:00+00:00","requireAt":"1997-10-24T00:00:00+00:00","shippedAt":"1997-09-30T00:00:00+00:00","shipTo":{"line1":"Mehrheimerstr. 369","city":"Köln","postalCode":"50739","country":"Germany"},"shipVia":"shippers/1","freight":145.63,"lines":[{"product":"products/40","productName":"Boston Crab Meat","pricePerUnit":18.4,"quantity":20,"discount":0.0},{"product":"products/47","productName":"Zaanse koeken","pricePerUnit":9.5,"quantity":40,"discount":0.0},{"product":"products/60","productName":"Camembert Pierrot","pricePerUnit":34.0,"quantity":30,"discount":0.0}],"id":"orders/437"}