{"company":"companies/75","employee":"employees/1","orderedAt":"1998-01-08T00:00:00+00:00","requireAt":"1998-02-05T00:00:00+00:00","shippedAt":"1998-01-15T00:00:00+00:00","shipTo":{"line1":"P.O. Box 555","city":"Lander","region":"WY","postalCode":"82520","country":"USA"},"shipVia":"shippers/1","freight":36.68,"lines":[{"product":"products/35","productName":"Steeleye Stout","pricePerUnit":18.0,"quantity":20,"discount":0.0},{"product":"products/51","productName":"Manjimup Dried Apples","pricePerUnit":53.0,"quantity":6,"discount":0.0}],"id":"orders/574"}