{"company":"companies/26","employee":"employees/3","orderedAt":"1998-01-29T00:00:00+00:00","requireAt":"1998-02-26T00:00:00+00:00","shippedAt":"1998-02-04T00:00:00+00:00","shipTo":{"line1":"54, rue Royale","city":"Nantes","postalCode":"44000","country":"France"},"shipVia":"shippers/3","freight":19.26,"lines":[{"product":"products/51","productName":"Manjimup Dried Apples","pricePerUnit":53.0,"quantity":3,"discount":0.0},{"product":"products/76","productName":"Lakkalikööri","pricePerUnit":18.0,"quantity":20,"discount":0.0}],"id":"orders/613"}