{"company":"companies/9","employee":"employees/9","orderedAt":"1998-02-05T00:00:00+00:00","requireAt":"1998-03-05T00:00:00+00:00","shippedAt":"1998-02-10T00:00:00+00:00","shipTo":{"line1":"12, rue des Bouchers","city":"Marseille","postalCode":"13008","country":"France"},"shipVia":"shippers/2","freight":112.27,"lines":[{"product":"products/6","productName":"Grandma's Boysenberry Spread","pricePerUnit":25.0,"quantity":50,"discount":0.05},{"product":"products/16","productName":"Pavlova","pricePerUnit":17.45,"quantity":12,"discount":0.05},{"product":"products/17","productName":"Alice Mutton","pricePerUnit":39.0,"quantity":16,"discount":0.05}],"id":"orders/624"}