{"company":"companies/71","employee":"employees/4","orderedAt":"1998-04-06T00:00:00+00:00","requireAt":"1998-05-04T00:00:00+00:00","shippedAt":"1998-04-16T00:00:00+00:00","shipTo":{"line1":"187 Suffolk Ln.","city":"Boise","region":"ID","postalCode":"83720","country":"USA"},"shipVia":"shippers/1","freight":141.16,"lines":[{"product":"products/13","productName":"Konbu","pricePerUnit":6.0,"quantity":56,"discount":0.0},{"product":"products/35","productName":"Steeleye Stout","pricePerUnit":18.0,"quantity":15,"discount":0.15},{"product":"products/42","productName":"Singaporean Hokkien Fried Mee","pricePerUnit":14.0,"quantity":24,"discount":0.15},{"product":"products/55","productName":"Pâté chinois","pricePerUnit":24.0,"quantity":40,"discount":0.0}],"id":"orders/755"}