{"company":"companies/8","employee":"employees/4","orderedAt":"1996-10-10T00:00:00+00:00","requireAt":"1996-11-07T00:00:00+00:00","shippedAt":"1996-10-14T00:00:00+00:00","shipTo":{"line1":"C/ Araquil, 67","city":"Madrid","postalCode":"28023","country":"Spain"},"shipVia":"shippers/2","freight":77.92,"lines":[{"product":"products/4","productName":"Chef Anton's Cajun Seasoning","pricePerUnit":17.6,"quantity":24,"discount":0.0},{"product":"products/57","productName":"Ravioli Angelo","pricePerUnit":15.6,"quantity":16,"discount":0.0},{"product":"products/75","productName":"Rhönbräu Klosterbier","pricePerUnit":6.2,"quantity":50,"discount":0.0}],"id":"orders/79"}